nasa_power-0.1.4.dist-info/licenses/LICENSE
nasapower/__init__.py
nasa_power-0.1.4.dist-info/METADATA
nasa_power-0.1.4.dist-info/WHEEL
nasa_power-0.1.4.dist-info/top_level.txt
nasa_power-0.1.4.dist-info/RECORD
