Metadata-Version: 2.4
Name: nasa-power
Version: 0.1.4
Summary: An unofficial Python client for the NASA Power API
Home-page: https://github.com/RubenVanEldik/nasa-power
Author: Ruben van Eldik
Author-email: ruben@vaneldik.ca
Project-URL: Docs, https://github.com/RubenVanEldik/nasa-power/blob/main/README.md
Classifier: Programming Language :: Python :: 3
Classifier: License :: OSI Approved :: MIT License
Classifier: Operating System :: OS Independent
Requires-Python: >=3.8
License-File: LICENSE
Requires-Dist: numpy>=1.20
Requires-Dist: pandas>=1.3
Requires-Dist: requests>=2.32
Dynamic: license-file
